realerikrani/projectclient/__init__.py
realerikrani/projectclient/auth_jwt.py
realerikrani/projectclient/cli.py
realerikrani/projectclient/client.py
realerikrani/projectclient/config.py
realerikrani/projectclient/create_new_key.py
realerikrani/projectclient/create_project_with_key.py
realerikrani/projectclient/delete_key.py
realerikrani/projectclient/delete_project.py
realerikrani/projectclient/model.py
realerikrani/projectclient/py.typed
realerikrani/projectclient/read_keys.py
realerikrani/projectclient/read_project.py
realerikrani_projectclient-1.0.0.dist-info/LICENSE-Apache-2.0
realerikrani_projectclient-1.0.0.dist-info/LICENSE-MIT-pyjwt
realerikrani_projectclient-1.0.0.dist-info/METADATA
realerikrani_projectclient-1.0.0.dist-info/NOTICE
realerikrani_projectclient-1.0.0.dist-info/WHEEL
realerikrani_projectclient-1.0.0.dist-info/entry_points.txt
realerikrani_projectclient-1.0.0.dist-info/top_level.txt
realerikrani_projectclient-1.0.0.dist-info/RECORD
