Metadata-Version: 2.2
Name: realerikrani-projectclient
Version: 1.0.0
Summary: API client & CLI for https://github.com/realerikrani/project
License: Apache-2.0
Project-URL: Repository, https://github.com/realerikrani/projectclient
Requires-Python: >=3.11
License-File: LICENSE-Apache-2.0
License-File: LICENSE-MIT-pyjwt
License-File: NOTICE
Requires-Dist: realerikrani-baseclient==1.*
Requires-Dist: pyjwt[crypto]==2.*
Requires-Dist: requests==2.*
